<theme>
  <variables>
    <systemName>Super Mario</systemName>
    <systemManufacturer>Nintendo</systemManufacturer>
    <systemReleaseYear>Various</systemReleaseYear>
    <systemReleaseYear lang="es">Varios</systemReleaseYear>
    <systemDescription>Super Mario (スーパーマリオ) (also known as Super Mario Bros. and Mario) is a platform game series developed and published by Nintendo and starring their mascot, Mario. The series was created by Japanese game designer Shigeru Miyamoto and is the flagship series of the greater Mario franchise. At least one Super Mario game has been released for every major Nintendo video game console. A limited number of Super Mario games have also released on non-Nintendo gaming platforms.</systemDescription>
    <systemDescription lang="es">Super Mario (スーパーマリオ) (también conocido como Super Mario Bros. y Mario) es una serie de videojuegos de plataformas creada por Nintendo protagonizada por su mascota, Mario. Es la serie central de la gran franquicia de Mario. Se ha lanzado al menos un juego de Super Mario para todas las principales consolas de videojuegos de Nintendo. Sin embargo, también se han lanzado varios videojuegos de Super Mario en plataformas de juegos que no son de Nintendo. Hay más de 20 juegos de la serie.</systemDescription>
    <systemHardwareType>Custom Collection</systemHardwareType>
    <systemHardwareType lang="es">Colección personalizada</systemHardwareType>
    <systemCoverSize>1-1</systemCoverSize>
    <systemCartSize>1-1</systemCartSize>
  </variables>
</theme>
